./.gitignore
./LICENSE
./PKG-INFO
./README.md
./__init__.py
./app.py
./config_load.py
./install.sh
./pyproject.toml
./requirements.txt
./config/config.toml
./static/app.js
./templates/index.html
fg_mobilejoystick-1.4.2.dist-info/METADATA
fg_mobilejoystick-1.4.2.dist-info/WHEEL
fg_mobilejoystick-1.4.2.dist-info/entry_points.txt
fg_mobilejoystick-1.4.2.dist-info/licenses/LICENSE
fg_mobilejoystick-1.4.2.dist-info/RECORD
