Metadata-Version: 2.4
Name: fg-mobileJoystick
Version: 1.4.2
Summary: Control FlightGear with mobile devices
Project-URL: Homepage, https://git.gzhang.xyz/GZhang/FG-mobile-joystick
Project-URL: Issues, https://sourceforge.net/p/mobilejoystick/tickets/
Author-email: Gordon Zhang <GordonZhang11@outlook.com>
License-Expression: GPL-3.0-or-later
License-File: LICENSE
Classifier: Operating System :: OS Independent
Classifier: Programming Language :: Python :: 3
Requires-Python: >=3.9
Requires-Dist: flask
Requires-Dist: flask-cors
Requires-Dist: flightgear-python
